README.rst
setup.py
pycogworks.logging.egg-info/PKG-INFO
pycogworks.logging.egg-info/SOURCES.txt
pycogworks.logging.egg-info/dependency_links.txt
pycogworks.logging.egg-info/namespace_packages.txt
pycogworks.logging.egg-info/top_level.txt
pycogworks/logging/__init__.py
pycogworks/logging/logging.py