Metadata-Version: 1.1
Name: pycogworks.logging
Version: 0.4.0
Summary: Logging functions used in the CogWorks lab.
Home-page: https://github.com/CogWorks/PyCogWorks
Author: Ryan Hope
Author-email: rmh3093@gmail.com
License: GPL-3
Platform: UNKNOWN
Classifier: License :: OSI Approved :: GNU General Public License (GPL)
Classifier: Programming Language :: Python :: 2
Classifier: Topic :: Scientific/Engineering
Classifier: Topic :: Utilities
